twat_hatch/themes/package.toml.j2
twat_hatch/themes/plugin.toml.j2
twat_hatch/themes/plugin_host.toml.j2
twat_hatch/themes/_shared/base.toml.j2
twat_hatch/themes/_shared/snippets/author.toml.j2
twat_hatch/themes/_shared/snippets/dependencies.toml.j2
twat_hatch/themes/_shared/snippets/development.toml.j2
twat_hatch/themes/_shared/snippets/features.toml.j2
twat_hatch/themes/_shared/snippets/package.toml.j2
twat_hatch/themes/_shared/snippets/tools.toml.j2
twat_hatch/themes/default/.pre-commit-config.yaml.j2
twat_hatch/themes/default/LICENSE.j2
twat_hatch/themes/default/README.md.j2
twat_hatch/themes/default/hidden.gitignore.j2
twat_hatch/themes/default/pyproject.toml.j2
twat_hatch/themes/default/.github/workflows/push.yml.j2
twat_hatch/themes/default/.github/workflows/release.yml.j2
twat_hatch/themes/default/dist/.gitkeep.j2
twat_hatch/themes/default/tests/test_package.py.j2
twat_hatch/themes/package/package.toml.j2
twat_hatch/themes/package/src/__package_name__/__package_name__.py.j2
twat_hatch/themes/plugin/README.md.j2
twat_hatch/themes/plugin/pyproject.toml.j2
twat_hatch/themes/plugin/src/__package_name__/__init__.py.j2
twat_hatch/themes/plugin_host/README.md.j2
twat_hatch/themes/plugin_host/pyproject.toml.j2
twat_hatch/themes/plugin_host/src/__init__.py.j2
twat_hatch/__init__.py
twat_hatch/__main__.py
twat_hatch/__version__.py
twat_hatch/config.py
twat_hatch/hatch.py
twat_hatch/utils.py
twat_hatch/themes/__init__.py
twat_hatch-2.6.2.dist-info/METADATA
twat_hatch-2.6.2.dist-info/WHEEL
twat_hatch-2.6.2.dist-info/entry_points.txt
twat_hatch-2.6.2.dist-info/licenses/LICENSE
twat_hatch-2.6.2.dist-info/RECORD
