Metadata-Version: 2.4
Name: twat-hatch
Version: 2.6.2
Summary: Plugin for twat that provides package initialization functionality
Project-URL: Documentation, https://github.com/twardoch/twat-hatch#readme
Project-URL: Issues, https://github.com/twardoch/twat-hatch/issues
Project-URL: Source, https://github.com/twardoch/twat-hatch
Author-email: Adam Twardoch <adam+github@twardoch.com>
License-Expression: MIT
License-File: LICENSE
Keywords: package-template,twat,twat-plugin
Classifier: Development Status :: 4 - Beta
Classifier: Intended Audience :: Developers
Classifier: License :: OSI Approved :: MIT License
Classifier: Programming Language :: Python :: 3
Classifier: Programming Language :: Python :: 3.10
Classifier: Programming Language :: Python :: 3.11
Classifier: Programming Language :: Python :: 3.12
Classifier: Topic :: Software Development :: Libraries :: Python Modules
Requires-Python: >=3.10
Requires-Dist: jinja2>=3.1.5
Requires-Dist: pydantic>=2.10.6
Requires-Dist: tomli>=2.0.0; python_version < '3.11'
Requires-Dist: twat>=1.8.1
Provides-Extra: all
Requires-Dist: jinja2>=3.1.5; extra == 'all'
Requires-Dist: pydantic>=2.10.6; extra == 'all'
Requires-Dist: tomli>=2.0.0; (python_version < '3.11') and extra == 'all'
Requires-Dist: twat>=1.8.1; extra == 'all'
Provides-Extra: dev
Requires-Dist: mypy>=1.15.0; extra == 'dev'
Requires-Dist: pre-commit>=4.1.0; extra == 'dev'
Requires-Dist: ruff>=0.9.6; extra == 'dev'
Provides-Extra: test
Requires-Dist: pytest-benchmark[histogram]>=5.1.0; extra == 'test'
Requires-Dist: pytest-cov>=6.0.0; extra == 'test'
Requires-Dist: pytest-xdist>=3.6.1; extra == 'test'
Requires-Dist: pytest>=8.3.4; extra == 'test'
